epho_sdk_testing_sdk/__init__.py
epho_sdk_testing_sdk/api_client.py
epho_sdk_testing_sdk/api_response.py
epho_sdk_testing_sdk/configuration.py
epho_sdk_testing_sdk/exceptions.py
epho_sdk_testing_sdk/py.typed
epho_sdk_testing_sdk/rest.py
epho_sdk_testing_sdk/api/__init__.py
epho_sdk_testing_sdk/api/gifs_api.py
epho_sdk_testing_sdk/api/stickers_api.py
epho_sdk_testing_sdk/models/__init__.py
epho_sdk_testing_sdk/models/get_gifs_by_id200_response.py
epho_sdk_testing_sdk/models/gif.py
epho_sdk_testing_sdk/models/gif_images.py
epho_sdk_testing_sdk/models/gif_images_downsized.py
epho_sdk_testing_sdk/models/gif_images_downsized_large.py
epho_sdk_testing_sdk/models/gif_images_downsized_medium.py
epho_sdk_testing_sdk/models/gif_images_downsized_small.py
epho_sdk_testing_sdk/models/gif_images_downsized_still.py
epho_sdk_testing_sdk/models/gif_images_fixed_height.py
epho_sdk_testing_sdk/models/gif_images_fixed_height_downsampled.py
epho_sdk_testing_sdk/models/gif_images_fixed_height_small.py
epho_sdk_testing_sdk/models/gif_images_fixed_height_small_still.py
epho_sdk_testing_sdk/models/gif_images_fixed_height_still.py
epho_sdk_testing_sdk/models/gif_images_fixed_width.py
epho_sdk_testing_sdk/models/gif_images_fixed_width_downsampled.py
epho_sdk_testing_sdk/models/gif_images_fixed_width_small.py
epho_sdk_testing_sdk/models/gif_images_fixed_width_small_still.py
epho_sdk_testing_sdk/models/gif_images_fixed_width_still.py
epho_sdk_testing_sdk/models/gif_images_looping.py
epho_sdk_testing_sdk/models/gif_images_original.py
epho_sdk_testing_sdk/models/gif_images_original_still.py
epho_sdk_testing_sdk/models/gif_images_preview.py
epho_sdk_testing_sdk/models/gif_images_preview_gif.py
epho_sdk_testing_sdk/models/image.py
epho_sdk_testing_sdk/models/meta.py
epho_sdk_testing_sdk/models/pagination.py
epho_sdk_testing_sdk/models/random_gif200_response.py
epho_sdk_testing_sdk/models/user.py
epho_sdk_testing_sdk-0.0.2.dist-info/METADATA
epho_sdk_testing_sdk-0.0.2.dist-info/WHEEL
epho_sdk_testing_sdk-0.0.2.dist-info/top_level.txt
epho_sdk_testing_sdk-0.0.2.dist-info/RECORD
